idun_agent_schema/__init__.py
idun_agent_schema/py.typed
idun_agent_schema/engine/__init__.py
idun_agent_schema/engine/adk.py
idun_agent_schema/engine/agent.py
idun_agent_schema/engine/agent_framework.py
idun_agent_schema/engine/api.py
idun_agent_schema/engine/base_agent.py
idun_agent_schema/engine/correction_agent.py
idun_agent_schema/engine/correction_agent_arguments.py
idun_agent_schema/engine/deep_research_agent.py
idun_agent_schema/engine/deep_research_agent_arguments.py
idun_agent_schema/engine/engine.py
idun_agent_schema/engine/guardrails.py
idun_agent_schema/engine/guardrails_type.py
idun_agent_schema/engine/guardrails_v2.py
idun_agent_schema/engine/haystack.py
idun_agent_schema/engine/langgraph.py
idun_agent_schema/engine/mcp_server.py
idun_agent_schema/engine/observability.py
idun_agent_schema/engine/observability_v2.py
idun_agent_schema/engine/server.py
idun_agent_schema/engine/templates.py
idun_agent_schema/engine/translation_agent.py
idun_agent_schema/engine/translation_agent_arguments.py
idun_agent_schema/manager/__init__.py
idun_agent_schema/manager/api.py
idun_agent_schema/manager/guardrail_configs.py
idun_agent_schema/manager/managed_agent.py
idun_agent_schema/manager/managed_guardrail.py
idun_agent_schema/manager/managed_mcp_server.py
idun_agent_schema/manager/managed_memory.py
idun_agent_schema/manager/managed_observability.py
idun_agent_schema/shared/__init__.py
idun_agent_schema/shared/base.py
idun_agent_schema-0.4.1.dist-info/METADATA
idun_agent_schema-0.4.1.dist-info/WHEEL
idun_agent_schema-0.4.1.dist-info/RECORD
