Metadata-Version: 2.4
Name: idun-agent-schema
Version: 0.4.1
Summary: Centralized Pydantic schema library for Idun Agent Engine and Manager
Project-URL: Homepage, https://github.com/geoffreyharrazi/idun-agent-platform
Project-URL: Repository, https://github.com/geoffreyharrazi/idun-agent-platform
Project-URL: Issues, https://github.com/geoffreyharrazi/idun-agent-platform/issues
Author-email: Idun Group <contact@idun-group.com>
License-Expression: GPL-3.0-only
Keywords: fastapi,idun,langgraph,pydantic,schemas
Classifier: License :: OSI Approved :: GNU General Public License v3 (GPLv3)
Classifier: Programming Language :: Python :: 3
Classifier: Programming Language :: Python :: 3 :: Only
Classifier: Programming Language :: Python :: 3.12
Classifier: Programming Language :: Python :: 3.13
Classifier: Typing :: Typed
Requires-Python: <3.14,>=3.12
Requires-Dist: pydantic-settings<3.0.0,>=2.7.0
Requires-Dist: pydantic<3.0.0,>=2.11.7
